{
  "annotations": {
    "list": []
  },
  "editable": true,
  "gnetId": null,
  "graphTooltip": 0,
  "id": null,
  "links": [],
  "panels": [
    {
      "collapsed": false,
      "gridPos": {
        "h": 1,
        "w": 24,
        "x": 0,
        "y": 0
      },
      "id": 100,
      "panels": [],
      "title": "Data Warehouse Overview",
      "type": "row"
    },
    {
      "datasource": "PostgreSQL",
      "description": "Total number of events transformed and loaded into the Data Warehouse.",
      "fieldConfig": {
        "defaults": {
          "color": {
            "mode": "fixed"
          },
          "mappings": [],
          "thresholds": {
            "mode": "absolute",
            "steps": [
              {
                "color": "green",
                "value": null
              }
            ]
          }
        },
        "overrides": []
      },
      "gridPos": {
        "h": 4,
        "w": 6,
        "x": 0,
        "y": 1
      },
      "id": 101,
      "options": {
        "colorMode": "background",
        "graphMode": "none",
        "justifyMode": "auto",
        "orientation": "auto",
        "reduceOptions": {
          "calcs": [
            "lastNotNull"
          ],
          "fields": "",
          "values": false
        },
        "textMode": "auto"
      },
      "pluginVersion": "8.3.3",
      "targets": [
        {
          "format": "table",
          "group": [],
          "metricColumn": "None",
          "rawQuery": true,
          "rawSql": "SELECT count(*) as value FROM fait_evenement",
          "refId": "A",
          "select": [
            [
              {
                "params": [
                  "value"
                ],
                "type": "column"
              }
            ]
          ],
          "table": "fait_evenement"
        }
      ],
      "title": "Total Events",
      "type": "stat"
    },
    {
      "datasource": "PostgreSQL",
      "description": "Total number of tables in the public schema.",
      "fieldConfig": {
        "defaults": {
          "color": {
            "mode": "fixed"
          },
          "mappings": [],
          "thresholds": {
            "mode": "absolute",
            "steps": [
              {
                "color": "blue",
                "value": null
              }
            ]
          }
        },
        "overrides": []
      },
      "gridPos": {
        "h": 4,
        "w": 6,
        "x": 6,
        "y": 1
      },
      "id": 102,
      "options": {
        "colorMode": "background",
        "graphMode": "none",
        "justifyMode": "auto",
        "orientation": "auto",
        "reduceOptions": {
          "calcs": [
            "lastNotNull"
          ],
          "fields": "",
          "values": false
        },
        "textMode": "auto"
      },
      "pluginVersion": "8.3.3",
      "targets": [
        {
          "format": "table",
          "group": [],
          "metricColumn": "None",
          "rawQuery": true,
          "rawSql": "SELECT count(*) as value FROM information_schema.tables WHERE table_schema = 'public'",
          "refId": "A",
          "select": [
            [
              {
                "params": [
                  "value"
                ],
                "type": "column"
              }
            ]
          ],
          "table": "information_schema.tables"
        }
      ],
      "title": "Tables count",
      "type": "stat"
    },
    {
      "datasource": "PostgreSQL",
      "description": "Number of locations (dim_lieu) stored.",
      "fieldConfig": {
        "defaults": {
          "color": {
            "mode": "fixed"
          },
          "mappings": [],
          "thresholds": {
            "mode": "absolute",
            "steps": [
              {
                "color": "purple",
                "value": null
              }
            ]
          }
        },
        "overrides": []
      },
      "gridPos": {
        "h": 4,
        "w": 6,
        "x": 12,
        "y": 1
      },
      "id": 103,
      "options": {
        "colorMode": "background",
        "graphMode": "none",
        "justifyMode": "auto",
        "orientation": "auto",
        "reduceOptions": {
          "calcs": [
            "lastNotNull"
          ],
          "fields": "",
          "values": false
        },
        "textMode": "auto"
      },
      "pluginVersion": "8.3.3",
      "targets": [
        {
          "format": "table",
          "group": [],
          "metricColumn": "None",
          "rawQuery": true,
          "rawSql": "SELECT count(*) as value FROM dim_lieu",
          "refId": "A"
        }
      ],
      "title": "Total Locations",
      "type": "stat"
    },
    {
      "datasource": "PostgreSQL",
      "description": "Breakdown of events by category.",
      "fieldConfig": {
        "defaults": {
          "color": {
            "mode": "palette-classic"
          },
          "custom": {
            "hideFrom": {
              "legend": false,
              "tooltip": false,
              "viz": false
            }
          },
          "mappings": []
        },
        "overrides": []
      },
      "gridPos": {
        "h": 4,
        "w": 6,
        "x": 18,
        "y": 1
      },
      "id": 104,
      "options": {
        "legend": {
          "displayMode": "list",
          "placement": "right"
        },
        "pieType": "pie",
        "reduceOptions": {
          "calcs": [
            "lastNotNull"
          ],
          "fields": "",
          "values": false
        },
        "tooltip": {
          "mode": "single",
          "sort": "none"
        }
      },
      "targets": [
        {
          "format": "table",
          "group": [],
          "metricColumn": "None",
          "rawQuery": true,
          "rawSql": "SELECT c.categorie, count(f.id) as count FROM fait_evenement f JOIN dim_categorie c ON f.categorie_id = c.id GROUP BY 1 ORDER BY 2 DESC",
          "refId": "A"
        }
      ],
      "title": "Events by Category",
      "type": "piechart"
    },
    {
      "collapsed": false,
      "gridPos": {
        "h": 1,
        "w": 24,
        "x": 0,
        "y": 5
      },
      "id": 20,
      "panels": [],
      "title": "Internet Connection Health (Speedtest)",
      "type": "row"
    },
    {
      "datasource": "PostgreSQL",
      "description": "Current download speed.",
      "fieldConfig": {
        "defaults": {
          "color": {
            "mode": "thresholds"
          },
          "mappings": [],
          "thresholds": {
            "mode": "absolute",
            "steps": [
              {
                "color": "red",
                "value": null
              },
              {
                "color": "orange",
                "value": 50
              },
              {
                "color": "green",
                "value": 100
              }
            ]
          },
          "unit": "bps"
        },
        "overrides": []
      },
      "gridPos": {
        "h": 6,
        "w": 4,
        "x": 0,
        "y": 6
      },
      "id": 2,
      "options": {
        "colorMode": "value",
        "graphMode": "area",
        "justifyMode": "auto",
        "orientation": "auto",
        "reduceOptions": {
          "calcs": [
            "lastNotNull"
          ],
          "fields": "",
          "values": false
        },
        "textMode": "auto"
      },
      "pluginVersion": "8.3.3",
      "targets": [
        {
          "format": "time_series",
          "group": [],
          "metricColumn": "None",
          "rawQuery": true,
          "rawSql": "SELECT timestamp AS \"time\", download FROM speedtest_results ORDER BY timestamp",
          "refId": "A",
          "select": [
            [
              {
                "params": [
                  "value"
                ],
                "type": "column"
              }
            ]
          ],
          "table": "speedtest_results",
          "timeColumn": "timestamp",
          "timeColumnType": "timestamp"
        }
      ],
      "title": "Download (Current)",
      "type": "stat"
    },
    {
      "datasource": "PostgreSQL",
      "description": "Current upload speed.",
      "fieldConfig": {
        "defaults": {
          "color": {
            "mode": "thresholds"
          },
          "mappings": [],
          "thresholds": {
            "mode": "absolute",
            "steps": [
              {
                "color": "red",
                "value": null
              },
              {
                "color": "orange",
                "value": 10
              },
              {
                "color": "green",
                "value": 20
              }
            ]
          },
          "unit": "bps"
        },
        "overrides": []
      },
      "gridPos": {
        "h": 6,
        "w": 4,
        "x": 4,
        "y": 6
      },
      "id": 4,
      "options": {
        "colorMode": "value",
        "graphMode": "area",
        "justifyMode": "auto",
        "orientation": "auto",
        "reduceOptions": {
          "calcs": [
            "lastNotNull"
          ],
          "fields": "",
          "values": false
        },
        "textMode": "auto"
      },
      "pluginVersion": "8.3.3",
      "targets": [
        {
          "format": "time_series",
          "group": [],
          "metricColumn": "None",
          "rawQuery": true,
          "rawSql": "SELECT timestamp AS \"time\", upload FROM speedtest_results ORDER BY timestamp",
          "refId": "A",
          "select": [
            [
              {
                "params": [
                  "value"
                ],
                "type": "column"
              }
            ]
          ],
          "table": "speedtest_results",
          "timeColumn": "timestamp",
          "timeColumnType": "timestamp"
        }
      ],
      "title": "Upload (Current)",
      "type": "stat"
    },
    {
      "datasource": "PostgreSQL",
      "description": "Current ping latency.",
      "fieldConfig": {
        "defaults": {
          "color": {
            "mode": "thresholds"
          },
          "mappings": [],
          "thresholds": {
            "mode": "absolute",
            "steps": [
              {
                "color": "green",
                "value": null
              },
              {
                "color": "orange",
                "value": 50
              },
              {
                "color": "red",
                "value": 100
              }
            ]
          },
          "unit": "ms"
        },
        "overrides": []
      },
      "gridPos": {
        "h": 6,
        "w": 4,
        "x": 8,
        "y": 6
      },
      "id": 6,
      "options": {
        "colorMode": "value",
        "graphMode": "area",
        "justifyMode": "auto",
        "orientation": "auto",
        "reduceOptions": {
          "calcs": [
            "lastNotNull"
          ],
          "fields": "",
          "values": false
        },
        "textMode": "auto"
      },
      "pluginVersion": "8.3.3",
      "targets": [
        {
          "format": "time_series",
          "group": [],
          "metricColumn": "None",
          "rawQuery": true,
          "rawSql": "SELECT timestamp AS \"time\", ping FROM speedtest_results ORDER BY timestamp",
          "refId": "A",
          "select": [
            [
              {
                "params": [
                  "value"
                ],
                "type": "column"
              }
            ]
          ],
          "table": "speedtest_results",
          "timeColumn": "timestamp",
          "timeColumnType": "timestamp"
        }
      ],
      "title": "Ping (Current)",
      "type": "stat"
    },
     {
      "datasource": "PostgreSQL",
      "description": "Average Download Speed in the last 24h.",
      "fieldConfig": {
        "defaults": {
          "color": {
            "mode": "thresholds"
          },
          "thresholds": {
            "mode": "absolute",
            "steps": [
              { "color": "red", "value": null },
              { "color": "green", "value": 100 }
            ]
          },
          "unit": "bps"
        }
      },
      "gridPos": { "h": 6, "w": 4, "x": 12, "y": 6 },
      "id": 201,
      "options": {
        "colorMode": "value",
        "graphMode": "none",
        "reduceOptions": { "calcs": ["mean"], "fields": "", "values": false }
      },
      "targets": [
        {
          "format": "time_series",
          "rawQuery": true,
          "rawSql": "SELECT timestamp AS \"time\", download FROM speedtest_results WHERE timestamp > current_date - interval '1 day'",
          "refId": "A"
        }
      ],
      "title": "Avg Download (24h)",
      "type": "stat"
    },
    {
      "datasource": "PostgreSQL",
      "description": "Maximum Download Speed in the last 24h.",
      "fieldConfig": {
        "defaults": {
          "color": { "mode": "thresholds" },
          "thresholds": {
            "mode": "absolute",
            "steps": [{ "color": "blue", "value": null }]
          },
          "unit": "bps"
        }
      },
      "gridPos": { "h": 6, "w": 4, "x": 16, "y": 6 },
      "id": 202,
      "options": {
        "colorMode": "value",
        "graphMode": "none",
        "reduceOptions": { "calcs": ["max"], "fields": "", "values": false }
      },
      "targets": [
        {
          "format": "time_series",
          "rawQuery": true,
          "rawSql": "SELECT timestamp AS \"time\", download FROM speedtest_results WHERE timestamp > current_date - interval '1 day'",
          "refId": "A"
        }
      ],
      "title": "Max Download (24h)",
      "type": "stat"
    },
     {
      "datasource": "PostgreSQL",
      "description": "Average Latency in the last 24h.",
      "fieldConfig": {
        "defaults": {
          "color": { "mode": "thresholds" },
          "thresholds": {
            "mode": "absolute",
            "steps": [{ "color": "green", "value": null }, { "color": "red", "value": 50 }]
          },
          "unit": "ms"
        }
      },
      "gridPos": { "h": 6, "w": 4, "x": 20, "y": 6 },
      "id": 203,
      "options": {
        "colorMode": "value",
        "graphMode": "none",
        "reduceOptions": { "calcs": ["mean"], "fields": "", "values": false }
      },
      "targets": [
        {
          "format": "time_series",
          "rawQuery": true,
          "rawSql": "SELECT timestamp AS \"time\", ping FROM speedtest_results WHERE timestamp > current_date - interval '1 day'",
          "refId": "A"
        }
      ],
      "title": "Avg Ping (24h)",
      "type": "stat"
    },
    {
      "collapsed": false,
      "gridPos": {
        "h": 1,
        "w": 24,
        "x": 0,
        "y": 14
      },
      "id": 22,
      "panels": [],
      "title": "Network Trends",
      "type": "row"
    },
    {
      "datasource": "PostgreSQL",
      "description": "Bandwidth usage history over time.",
      "fieldConfig": {
        "defaults": {
          "color": {
            "mode": "palette-classic"
          },
          "custom": {
            "axisLabel": "Speed",
            "axisPlacement": "auto",
            "drawStyle": "line",
            "fillOpacity": 10,
            "lineInterpolation": "smooth",
            "lineWidth": 2,
            "unit": "bps"
          },
          "mappings": [],
          "thresholds": {
            "mode": "absolute",
            "steps": [
              {
                "color": "green",
                "value": null
              }
            ]
          }
        },
        "overrides": []
      },
      "gridPos": {
        "h": 8,
        "w": 12,
        "x": 0,
        "y": 15
      },
      "id": 8,
      "options": {
        "legend": {
          "calcs": ["max", "mean"],
          "displayMode": "table",
          "placement": "bottom"
        },
        "tooltip": {
          "mode": "multi",
          "sort": "none"
        }
      },
      "targets": [
        {
          "format": "time_series",
          "group": [],
          "metricColumn": "None",
          "rawQuery": true,
          "rawSql": "SELECT timestamp AS \"time\", download AS \"Download\" FROM speedtest_results ORDER BY timestamp",
          "refId": "A"
        },
        {
          "format": "time_series",
          "group": [],
          "metricColumn": "None",
          "rawQuery": true,
          "rawSql": "SELECT timestamp AS \"time\", upload AS \"Upload\" FROM speedtest_results ORDER BY timestamp",
          "refId": "B"
        }
      ],
      "title": "Bandwidth History",
      "type": "timeseries"
    },
    {
      "datasource": "PostgreSQL",
      "description": "Latency history over time. Lower is better.",
      "fieldConfig": {
        "defaults": {
          "color": {
            "mode": "palette-classic"
          },
          "custom": {
            "axisLabel": "Latency (ms)",
            "axisPlacement": "auto",
            "drawStyle": "line",
            "fillOpacity": 10,
            "lineInterpolation": "linear",
            "lineWidth": 1,
            "unit": "ms"
          },
          "mappings": [],
          "thresholds": {
            "mode": "absolute",
            "steps": [
              {
                "color": "green",
                "value": null
              }
            ]
          }
        },
        "overrides": []
      },
      "gridPos": {
        "h": 8,
        "w": 12,
        "x": 12,
        "y": 15
      },
      "id": 10,
      "options": {
        "legend": {
          "calcs": ["min", "max", "mean"],
          "displayMode": "table",
          "placement": "bottom"
        },
        "tooltip": {
          "mode": "single",
          "sort": "none"
        }
      },
      "targets": [
        {
          "format": "time_series",
          "group": [],
          "metricColumn": "None",
          "rawQuery": true,
          "rawSql": "SELECT timestamp AS \"time\", ping AS \"Latency\" FROM speedtest_results ORDER BY timestamp",
          "refId": "A"
        }
      ],
      "title": "Latency History",
      "type": "timeseries"
    },
    {
      "collapsed": true,
      "gridPos": {
        "h": 1,
        "w": 24,
        "x": 0,
        "y": 23
      },
      "id": 24,
      "panels": [
        {
          "datasource": "PostgreSQL",
          "fieldConfig": {
            "defaults": {
              "color": {
                "mode": "thresholds"
              },
              "mappings": [],
              "thresholds": {
                "mode": "absolute",
                "steps": [
                  {
                    "color": "green",
                    "value": null
                  },
                  {
                    "color": "red",
                    "value": 80
                  }
                ]
              }
            },
            "overrides": []
          },
          "gridPos": {
            "h": 8,
            "w": 24,
            "x": 0,
            "y": 24
          },
          "id": 12,
          "options": {
            "showHeader": true
          },
          "pluginVersion": "8.3.3",
          "targets": [
            {
              "format": "table",
              "group": [],
              "metricColumn": "None",
              "rawQuery": true,
              "rawSql": "SELECT timestamp, download AS \"Download\", upload AS \"Upload\", ping AS \"Ping\", server_name FROM speedtest_results ORDER BY timestamp DESC LIMIT 50",
              "refId": "A"
            }
          ],
          "title": "Raw Data Log",
          "type": "table"
        }
      ],
      "title": "Detailed Data Log",
      "type": "row"
    }
  ],
  "refresh": "5s",
  "schemaVersion": 30,
  "style": "dark",
  "tags": [
    "speedtest",
    "postgres",
    "events"
  ],
  "templating": {
    "list": []
  },
  "time": {
    "from": "now-12h",
    "to": "now"
  },
  "timepicker": {},
  "timezone": "",
  "title": "PostgreSQL: Events & SpeedTest",
  "uid": "speedtest-pg",
  "version": 2
}
